mydemode/__init__.py
mydemode/testimport.py
mydemode/imp/__init__.py
mydemode/imp/fo.py
mydemode/rest/__init__.py
mydemode/rest/epf/__init__.py
mydemode/rest/epf/epf_rest.py
mydemode-0.0.3.dist-info/LICENSE
mydemode-0.0.3.dist-info/METADATA
mydemode-0.0.3.dist-info/WHEEL
mydemode-0.0.3.dist-info/top_level.txt
mydemode-0.0.3.dist-info/RECORD
