Metadata-Version: 2.1
Name: mydemode
Version: 0.0.3
Summary: Sample test package for DE APIs POC
Home-page: https://github.com/sharmasumit64/mydemode
Author: Sumit Sharma
Author-email: sharmasumit64@gmail.com
License: UNKNOWN
Platform: UNKNOWN
Classifier: Programming Language :: Python :: 3
Classifier: Programming Language :: Python :: 2.7
Classifier: Operating System :: OS Independent
Requires-Python: >=2.7
